serial_port_change/__init__.py
serial_port_change-1.0.6.dist-info/METADATA
serial_port_change-1.0.6.dist-info/WHEEL
serial_port_change-1.0.6.dist-info/entry_points.txt
serial_port_change-1.0.6.dist-info/licenses/LICENSE
serial_port_change-1.0.6.dist-info/RECORD
