Metadata-Version: 2.4
Name: serial-port-change
Version: 1.0.6
Summary: Monitor the serial ports in Windows and detect and display changes
Project-URL: Homepage, https://github.com/dbwalker0min/serial-port-change
Project-URL: Repository, https://github.com/dbwalker0min/serial-port-change
Author-email: David Walker <dbwalker0min@gmail.com>
License: MIT License
License-File: LICENSE
Requires-Python: >=3.12
Requires-Dist: pyserial>=3.5
